{
    "knob_name": "bonus-inst-threshold",
    "original_val": "1",
    "knob_values": [
        0,
        1,
        2,
        3,
        4,
        5,
        6,
        7,
        8,
        9,
        10,
        11,
        20
    ],
    "stats": [
        "Number of MayAlias results (aa)",
        "Number of MustAlias results (aa)",
        "Number of NoAlias results (aa)",
        "Number of instructions CSE'd (early-cse)",
        "Number of instructions simplified or DCE'd (early-cse)",
        "Number of dead inst eliminated (instcombine)",
        "Number of loop exits without predictable exit counts (scalar-evolution)",
        "Number of branches folded into predecessor basic block (simplifycfg)",
        "Number of blocks simplified (simplifycfg)",
        "Number of speculative executed instructions (simplifycfg)",
        "Number of comparisons propagated (correlated-value-propagation)",
        "Number of instructions deleted (gvn)",
        "Number of loads deleted (gvn)",
        "Number of instructions simplified (gvn)",
        "Number of loads PRE'd (gvn)",
        "Number of instructions sunk (instcombine)",
        "Number of jumps threaded (jump-threading)",
        "Number of common instruction 'blocks' hoisted up to the begin block (simplifycfg)",
        "Number of common instructions hoisted up to the begin block (simplifycfg)",
        "Number of value comparisons folded into predecessor basic blocks (simplifycfg)",
        "Number of pointers not captured (capture-tracking)",
        "Number of basic blocks unreachable (sccp)",
        "Number of instructions removed (sccp)",
        "Number of instructions removed (unused) (bdce)"
    ],
    "stats_val": {
        "Number of MayAlias results (aa)": {
            "normalized_values": [
                1.0,
                0.0,
                0.019138755980861243,
                0.019138755980861243,
                0.019138755980861243,
                0.019138755980861243,
                0.0430622009569378,
                0.0430622009569378,
                0.0430622009569378,
                0.0430622009569378,
                0.0430622009569378,
                0.0430622009569378,
                0.0430622009569378
            ],
            "min": 1317.13,
            "max": 1319.22
        },
        "Number of MustAlias results (aa)": {
            "normalized_values": [
                1.0,
                0.15384615384615385,
                0.15384615384615385,
                0.2692307692307692,
                0.15384615384615385,
                0.0,
                0.0,
                0.0,
                0.0,
                0.0,
                0.0,
                0.0,
                0.0
            ],
            "min": 353.48,
            "max": 353.74
        },
        "Number of NoAlias results (aa)": {
            "normalized_values": [
                0.0,
                0.1728395061728395,
                0.2222222222222222,
                0.18518518518518517,
                0.2222222222222222,
                0.9259259259259259,
                1.0,
                1.0,
                1.0,
                1.0,
                1.0,
                1.0,
                1.0
            ],
            "min": 7475.66,
            "max": 7476.47
        },
        "Number of instructions CSE'd (early-cse)": {
            "normalized_values": [
                0.08411214953271028,
                0.0,
                0.1588785046728972,
                0.11214953271028037,
                0.11214953271028037,
                0.11214953271028037,
                0.11214953271028037,
                0.11214953271028037,
                0.11214953271028037,
                0.11214953271028037,
                0.11214953271028037,
                0.11214953271028037,
                1.0
            ],
            "min": 159.02,
            "max": 160.09
        },
        "Number of instructions simplified or DCE'd (early-cse)": {
            "normalized_values": [
                0.0,
                0.8775510204081632,
                0.8775510204081632,
                0.8979591836734694,
                0.9081632653061225,
                0.9285714285714286,
                0.9897959183673469,
                1.0,
                1.0,
                1.0,
                1.0,
                1.0,
                1.0
            ],
            "min": 364.85,
            "max": 369.75
        },
        "Number of dead inst eliminated (instcombine)": {
            "normalized_values": [
                0.0,
                0.9085631349782293,
                0.9172714078374455,
                0.9709724238026125,
                0.9782293178519593,
                0.9927431059506531,
                0.9927431059506531,
                1.0,
                1.0,
                1.0,
                1.0,
                1.0,
                1.0
            ],
            "min": 448.08,
            "max": 454.97
        },
        "Number of loop exits without predictable exit counts (scalar-evolution)": {
            "normalized_values": [
                1.0,
                0.5714285714285714,
                0.0,
                0.0,
                0.0,
                0.0,
                0.0,
                0.0,
                0.0,
                0.0,
                0.0,
                0.0,
                0.0
            ],
            "min": 201.02,
            "max": 202.42
        },
        "Number of branches folded into predecessor basic block (simplifycfg)": {
            "normalized_values": [
                0.0,
                0.7063670411985019,
                0.80374531835206,
                0.8344569288389513,
                0.8404494382022472,
                0.8606741573033708,
                0.9138576779026217,
                0.9325842696629213,
                0.9333333333333333,
                0.9370786516853933,
                0.946067415730337,
                0.950561797752809,
                1.0
            ],
            "min": 8.11,
            "max": 21.46
        },
        "Number of blocks simplified (simplifycfg)": {
            "normalized_values": [
                0.0,
                0.3946360153256705,
                0.6340996168582376,
                0.7413793103448276,
                0.7375478927203065,
                0.7816091954022989,
                0.8333333333333334,
                0.8601532567049809,
                0.8620689655172413,
                0.8620689655172413,
                0.8850574712643678,
                0.9022988505747126,
                1.0
            ],
            "min": 836.41,
            "max": 841.63
        },
        "Number of speculative executed instructions (simplifycfg)": {
            "normalized_values": [
                1.0,
                0.375,
                0.0,
                0.125,
                0.125,
                0.125,
                0.375,
                0.375,
                0.375,
                0.375,
                0.375,
                0.375,
                0.375
            ],
            "min": 14.03,
            "max": 14.43
        },
        "Number of comparisons propagated (correlated-value-propagation)": {
            "normalized_values": [
                1.0,
                0.0,
                0.0,
                0.25,
                0.25,
                0.25,
                0.25,
                0.25,
                0.25,
                0.25,
                0.25,
                0.25,
                0.25
            ],
            "min": 0.56,
            "max": 0.64
        },
        "Number of instructions deleted (gvn)": {
            "normalized_values": [
                1.0,
                0.12658227848101267,
                0.0759493670886076,
                0.0759493670886076,
                0.0759493670886076,
                0.0759493670886076,
                0.0759493670886076,
                0.0759493670886076,
                0.0759493670886076,
                0.0759493670886076,
                0.0759493670886076,
                0.0759493670886076,
                0.0
            ],
            "min": 107.61,
            "max": 108.4
        },
        "Number of loads deleted (gvn)": {
            "normalized_values": [
                1.0,
                0.3333333333333333,
                0.0,
                0.0,
                0.0,
                0.0,
                0.0,
                0.0,
                0.0,
                0.0,
                0.0,
                0.0,
                0.0
            ],
            "min": 9.64,
            "max": 9.76
        },
        "Number of instructions simplified (gvn)": {
            "normalized_values": [
                1.0,
                0.21428571428571427,
                0.21428571428571427,
                0.21428571428571427,
                0.21428571428571427,
                0.21428571428571427,
                0.21428571428571427,
                0.21428571428571427,
                0.21428571428571427,
                0.21428571428571427,
                0.21428571428571427,
                0.21428571428571427,
                0.0
            ],
            "min": 62.39,
            "max": 62.67
        },
        "Number of loads PRE'd (gvn)": {
            "normalized_values": [
                1.0,
                0.0,
                0.19047619047619047,
                0.19047619047619047,
                0.19047619047619047,
                0.19047619047619047,
                0.19047619047619047,
                0.19047619047619047,
                0.19047619047619047,
                0.19047619047619047,
                0.19047619047619047,
                0.19047619047619047,
                0.19047619047619047
            ],
            "min": 11.35,
            "max": 11.56
        },
        "Number of instructions sunk (instcombine)": {
            "normalized_values": [
                0.0,
                0.1631663974151858,
                0.3166397415185784,
                0.3166397415185784,
                0.3554119547657512,
                0.43295638126009695,
                0.5137318255250404,
                0.5105008077544426,
                0.5105008077544426,
                0.5105008077544426,
                0.5105008077544426,
                0.5105008077544426,
                1.0
            ],
            "min": 45.49,
            "max": 51.68
        },
        "Number of jumps threaded (jump-threading)": {
            "normalized_values": [
                1.0,
                0.35051546391752575,
                0.14432989690721648,
                0.12371134020618557,
                0.12371134020618557,
                0.12371134020618557,
                0.12371134020618557,
                0.12371134020618557,
                0.12371134020618557,
                0.12371134020618557,
                0.12371134020618557,
                0.12371134020618557,
                0.0
            ],
            "min": 43.39,
            "max": 44.36
        },
        "Number of common instruction 'blocks' hoisted up to the begin block (simplifycfg)": {
            "normalized_values": [
                0.0,
                0.6363636363636364,
                0.6363636363636364,
                0.6363636363636364,
                0.6363636363636364,
                0.8181818181818182,
                0.8181818181818182,
                0.7272727272727273,
                0.7272727272727273,
                0.7272727272727273,
                0.7272727272727273,
                1.0,
                1.0
            ],
            "min": 20.85,
            "max": 21.07
        },
        "Number of common instructions hoisted up to the begin block (simplifycfg)": {
            "normalized_values": [
                0.0,
                0.6153846153846154,
                0.5128205128205128,
                0.5128205128205128,
                0.5128205128205128,
                0.5641025641025641,
                0.5641025641025641,
                0.6153846153846154,
                0.6153846153846154,
                0.6153846153846154,
                0.6153846153846154,
                1.0,
                1.0
            ],
            "min": 55.75,
            "max": 56.53
        },
        "Number of value comparisons folded into predecessor basic blocks (simplifycfg)": {
            "normalized_values": [
                1.0,
                0.056818181818181816,
                0.056818181818181816,
                0.056818181818181816,
                0.045454545454545456,
                0.045454545454545456,
                0.045454545454545456,
                0.03409090909090909,
                0.03409090909090909,
                0.03409090909090909,
                0.03409090909090909,
                0.03409090909090909,
                0.0
            ],
            "min": 8.6,
            "max": 13.0
        },
        "Number of pointers not captured (capture-tracking)": {
            "normalized_values": [
                0.6,
                1.0,
                0.6666666666666666,
                1.0,
                1.0,
                1.0,
                0.0,
                0.0,
                0.0,
                0.0,
                0.0,
                0.0,
                0.0
            ],
            "min": 41.81,
            "max": 41.96
        },
        "Number of basic blocks unreachable (sccp)": {
            "normalized_values": [
                1.0,
                0.3333333333333333,
                0.0,
                0.0,
                0.0,
                0.0,
                0.0,
                0.0,
                0.0,
                0.0,
                0.0,
                0.0,
                0.0
            ],
            "min": 25.09,
            "max": 25.24
        },
        "Number of instructions removed (sccp)": {
            "normalized_values": [
                1.0,
                0.234375,
                0.0,
                0.0,
                0.0,
                0.0,
                0.0,
                0.0,
                0.0,
                0.0,
                0.0,
                0.0,
                0.0
            ],
            "min": 95.54,
            "max": 96.18
        },
        "Number of instructions removed (unused) (bdce)": {
            "normalized_values": [
                0.0,
                0.5555555555555556,
                1.0,
                1.0,
                1.0,
                1.0,
                1.0,
                1.0,
                1.0,
                1.0,
                1.0,
                1.0,
                1.0
            ],
            "min": 7.46,
            "max": 7.55
        }
    },
    "time_arr": [
        1.0,
        0.0,
        0.03777087855103938,
        0.03956438986992887,
        0.05068587749886444,
        0.06117095592617565,
        0.04387590806715736,
        0.05563264935268814,
        0.06079904716315009,
        0.046287474193610734,
        0.05538413130655711,
        0.043886591916479645,
        0.05714463668413297
    ],
    "time_min": 0.040298030275,
    "time_max": 0.060026094599999996
}